.travis.yml
.zopeskel
CHANGES.txt
LICENSE.txt
Makefile
README.txt
setup.cfg
setup.py
version.txt
docs/LICENSE.GPL
docs/LICENSE.txt
docs/Makefile
docs/source/conf.py
docs/source/index.rst
docs/source/_static/.empty
docs/source/_templates/indexsidebar.html
docs/source/_themes/bootstrap.zip
raisin/__init__.py
raisin.box.egg-info/PKG-INFO
raisin.box.egg-info/SOURCES.txt
raisin.box.egg-info/dependency_links.txt
raisin.box.egg-info/entry_points.txt
raisin.box.egg-info/namespace_packages.txt
raisin.box.egg-info/not-zip-safe
raisin.box.egg-info/requires.txt
raisin.box.egg-info/top_level.txt
raisin/box/__init__.py
raisin/box/boxes.ini
raisin/box/boxes.py
raisin/box/config.py
raisin/box/resources.ini
raisin/box/tests/test_box.py